semanticanalyser/__init__.py
semanticanalyser/analyser.py
semanticanalyser_py-0.1.7.dist-info/licenses/LICENSE
semanticanalyser_py-0.1.7.dist-info/METADATA
semanticanalyser_py-0.1.7.dist-info/WHEEL
semanticanalyser_py-0.1.7.dist-info/top_level.txt
semanticanalyser_py-0.1.7.dist-info/RECORD
