Metadata-Version: 2.4
Name: semanticanalyser-py
Version: 0.1.7
Summary: A Python binding for the Semantic Analyser service maintained by BODC
Author: Ahmad Mahmoud (CNR internship)
Author-email: ahmad.mahmoud@edu.unifi.it
Maintainer: CNR-IIA Sede di Firenze
Maintainer-email: sede.firenze@iia.cnr.it
License: GPL-3.0
Project-URL: Homepage, https://github.com/ESSI-Lab/semanticanalyser-py
Project-URL: Source, https://github.com/ESSI-Lab/semanticanalyser-py
Project-URL: Tracker, https://github.com/ESSI-Lab/semanticanalyser-py/issues
Classifier: Programming Language :: Python :: 3
Classifier: Programming Language :: Python :: 3 :: Only
Classifier: Programming Language :: Python :: 3.8
Classifier: Programming Language :: Python :: 3.9
Classifier: Programming Language :: Python :: 3.10
Classifier: Programming Language :: Python :: 3.11
Classifier: Programming Language :: Python :: 3.12
Classifier: Programming Language :: Python :: 3.13
Classifier: Operating System :: OS Independent
Classifier: Intended Audience :: Developers
Classifier: Topic :: Software Development :: Libraries
Requires-Python: >=3.8
License-File: LICENSE
Requires-Dist: requests>=2.25.0
Dynamic: author
Dynamic: author-email
Dynamic: classifier
Dynamic: description
Dynamic: description-content-type
Dynamic: license
Dynamic: license-file
Dynamic: maintainer
Dynamic: maintainer-email
Dynamic: project-url
Dynamic: requires-dist
Dynamic: requires-python
Dynamic: summary
